[
  {
    "name": "wfweg",
    "age": "18",
    "major": "finance",
    "q1": "rarely",
    "q2": "shopee",
    "q3": "rarelyweg",
    "q4": "shopeeweg",
    "q5": "rarelywegweg",
    "q6": "package",
    "q7": "mid",
    "q8": "store-only",
    "q9": "beauty-app",
    "q10": "discount",
    "q11": "rating",
    "rating1": "3",
    "rating2": "4",
    "rating3": "3",
    "rating4": "5",
    "rating5": "4",
    "id": 1760480686019,
    "timestamp": "2025-10-14T22:24:46.019Z"
  },
  {
    "name": "Jdjeh",
    "age": "18",
    "major": "accounting",
    "q1": "weekly",
    "q2": "tiktok",
    "q3": "weeklydhjd",
    "q4": "tiktokshhs",
    "q5": "Hdjehe",
    "q6": "variety",
    "q7": "mid",
    "q8": "store-only",
    "q9": "brand-site",
    "q10": "limited",
    "q11": "rating",
    "rating1": "5",
    "rating2": "5",
    "rating3": "5",
    "rating4": "5",
    "rating5": "5",
    "id": 1760481527063,
    "timestamp": "2025-10-14T22:38:47.063Z"
  },
  {
    "name": "erghrehe",
    "age": "18",
    "major": "finance",
    "q1": "monthly",
    "q2": "tiktok",
    "q3": "monthlyerhe",
    "q4": "tiktokrhrehe",
    "q5": "monthlyerherehe",
    "q6": "variety",
    "q7": "mid",
    "q8": "store-only",
    "q9": "beauty-app",
    "q10": "freebie",
    "q11": "return",
    "rating1": "4",
    "rating2": "4",
    "rating3": "3",
    "rating4": "4",
    "rating5": "3",
    "rating6": "4",
    "id": 1760490694869,
    "timestamp": "2025-10-15T01:11:34.869Z"
  },
  {
    "name": "tseet",
    "age": "18",
    "major": "finance",
    "q1": "weekly",
    "q2": "tiktok",
    "q3": "weeklyestse",
    "q4": "tiktoktsets",
    "q5": "weeklyestsesetse",
    "q6": "variety",
    "q7": "premium",
    "q8": "store-only",
    "q9": "brand-site",
    "q10": "limited",
    "q11": "return",
    "rating1": "5",
    "rating2": "4",
    "rating3": "4",
    "rating4": "5",
    "rating5": "5",
    "rating6": "5",
    "id": 1760491443805,
    "timestamp": "2025-10-15T01:24:03.805Z"
  },
  {
    "name": "Iphone",
    "age": "19",
    "major": "accounting",
    "q1": "monthly",
    "q2": "lazada",
    "q3": "monthlyhdje",
    "q4": "lazadakdke",
    "q5": "Jsjeje",
    "q6": "variety",
    "q7": "mid",
    "q8": "both",
    "q9": "brand-site",
    "q10": "freebie",
    "q11": "return",
    "rating1": "4",
    "rating2": "5",
    "rating3": "4",
    "rating4": "5",
    "rating5": "5",
    "rating6": "4",
    "id": 1760492785498,
    "timestamp": "2025-10-15T01:46:25.498Z"
  },
  {
    "name": "demo-froms",
    "age": "18",
    "major": "finance",
    "q1": "rarely",
    "q2": "tiktok",
    "q3": "rarelyfef",
    "q4": "tiktokefe",
    "q5": "rarelyfefeffe",
    "q6": "variety",
    "q7": "premium",
    "q8": "store-only",
    "q9": "brand-site",
    "q10": "freebie",
    "q11": "authentic",
    "rating1": "5",
    "rating2": "5",
    "rating3": "5",
    "rating4": "5",
    "rating5": "5",
    "rating6": "5",
    "id": 1760493753691,
    "timestamp": "2025-10-15T02:02:33.691Z"
  }
]